secbatch/__init__.py
secbatch/main.py
secbatch/workflow.py
secbatch/example_input/patient.txt
secbatch-0.1.0.dist-info/METADATA
secbatch-0.1.0.dist-info/WHEEL
secbatch-0.1.0.dist-info/entry_points.txt
secbatch-0.1.0.dist-info/top_level.txt
secbatch-0.1.0.dist-info/RECORD
