Metadata-Version: 2.4
Name: secbatch
Version: 0.1.0
Summary: A tool to securely run jobs on Slurm clusters.
License: MIT License
Classifier: Programming Language :: Python :: 3
Classifier: License :: OSI Approved :: MIT License
Classifier: Operating System :: OS Independent
Classifier: Topic :: Security
Classifier: Topic :: System :: Clustering
Classifier: Topic :: System :: Distributed Computing
Requires-Python: >=3.8
Requires-Dist: paramiko
Requires-Dist: python-gnupg
Requires-Dist: importlib-resources; python_version < "3.9"
